scrapy_proxy_pool/__init__.py
scrapy_proxy_pool/middlewares.py
scrapy_proxy_pool/policy.py
scrapy_proxy_pool-0.1.8.dist-info/METADATA
scrapy_proxy_pool-0.1.8.dist-info/WHEEL
scrapy_proxy_pool-0.1.8.dist-info/top_level.txt
scrapy_proxy_pool-0.1.8.dist-info/RECORD
